subtimizer/__init__.py
subtimizer/cli.py
subtimizer/manager.py
subtimizer/utils.py
subtimizer/templates/__init__.py
subtimizer/templates/af2init_guess_validate_template.sh
subtimizer/templates/cluster_template.sh
subtimizer/templates/design_parallel_template.sh
subtimizer/templates/design_template.sh
subtimizer/templates/fix_pdb_template.sh
subtimizer/templates/fold_parallel_template.sh
subtimizer/templates/fold_template.sh
subtimizer/templates/fold_validation_parallel_template.sh
subtimizer/templates/fold_validation_template.sh
subtimizer/templates/ipsae_template.sh
subtimizer/workflow/__init__.py
subtimizer/workflow/analysis.py
subtimizer/workflow/clustering.py
subtimizer/workflow/design.py
subtimizer/workflow/folding.py
subtimizer/workflow/ipsae_runner.py
subtimizer/workflow/pdb_utils.py
subtimizer/workflow/preparation.py
subtimizer/workflow/reporting.py
subtimizer/workflow/setup.py
subtimizer/workflow/validation.py
subtimizer-1.0.0.dist-info/METADATA
subtimizer-1.0.0.dist-info/WHEEL
subtimizer-1.0.0.dist-info/entry_points.txt
subtimizer-1.0.0.dist-info/licenses/LICENSE
subtimizer-1.0.0.dist-info/RECORD
