Metadata-Version: 2.4
Name: subtimizer
Version: 1.0.0
Summary: A Computational Workflow for Structure-Guided Design of Potent and Selective Kinase Peptide Substrates
Project-URL: Homepage, https://github.com/abeebyekeen/subtimizer
Project-URL: Publication, https://doi.org/10.1101/2025.07.04.663216
Author-email: Abeeb Yekeen <Abeeb.Yekeen@UTSouthwestern.edu>
License-Expression: MIT
License-File: LICENSE
Classifier: Programming Language :: Python :: 3
Requires-Python: >=3.9
Requires-Dist: biopython
Requires-Dist: click
Requires-Dist: colorcet
Requires-Dist: matplotlib
Requires-Dist: numpy
Requires-Dist: pandas
Requires-Dist: scipy
Requires-Dist: seaborn
Requires-Dist: weblogo
